mimo_audio/mimo_audio.py
mimo_audio/modeling_mimo_audio.py
mimo_audio/process_speechdata.py
mimo_audio/templates.py
mimo_audio_tokenizer/__init__.py
mimo_audio_tokenizer/configuration_audio_tokenizer.py
mimo_audio_tokenizer/modeling_audio_tokenizer.py
mimo_audio_tokenizer/modeling_rope_utils.py
mimo_audio_tokenizer/quantization.py
tts_webui_mimo_audio-0.0.3.dist-info/licenses/LICENSE
tts_webui_mimo_audio-0.0.3.dist-info/METADATA
tts_webui_mimo_audio-0.0.3.dist-info/WHEEL
tts_webui_mimo_audio-0.0.3.dist-info/top_level.txt
tts_webui_mimo_audio-0.0.3.dist-info/RECORD
