Metadata-Version: 2.4
Name: tts-webui.mimo_audio
Version: 0.0.3
Requires-Python: <3.13,>=3.10
License-File: LICENSE
Requires-Dist: torch>=2.6.0
Requires-Dist: torchaudio>=2.6.0
Requires-Dist: transformers>=4.49.0
Requires-Dist: gradio
Dynamic: license-file
